auto2/continuations/base.py
auto2/continuations/fixed_points.py
auto2/continuations/periodic_orbits.py
auto2/diagrams/bifurcations.py
auto2/parsers/config.py
auto_auto-0.5.7.dist-info/licenses/LICENSE.txt
auto_auto-0.5.7.dist-info/METADATA
auto_auto-0.5.7.dist-info/WHEEL
auto_auto-0.5.7.dist-info/top_level.txt
auto_auto-0.5.7.dist-info/RECORD
