Metadata-Version: 2.4
Name: auto-AUTO
Version: 0.5.7
Summary: An AUTO-07p automatic search algorithm codebase
Author-email: Jonathan Demaeyer <jodemaey@meteo.be>, Oísin Hamilton <oisin.hamilton@meteo.be>
License: MIT License
Project-URL: homepage, https://github.com/Climdyn/auto-AUTO
Project-URL: documentation, https://climdyn.github.io/auto-AUTO/
Keywords: bifurcation,bifurcation analysis,AUTO,automation
Classifier: License :: OSI Approved :: MIT License
Classifier: Programming Language :: Python
Classifier: Programming Language :: Python :: 3
Classifier: Programming Language :: Python :: 3.10
Classifier: Programming Language :: Python :: 3.11
Classifier: Programming Language :: Python :: 3.12
Classifier: Operating System :: OS Independent
Classifier: Development Status :: 5 - Production/Stable
Classifier: Framework :: Jupyter
Classifier: Intended Audience :: Science/Research
Classifier: Topic :: Scientific/Engineering
Classifier: Topic :: Scientific/Engineering :: Mathematics
Requires-Python: >=3.10
License-File: LICENSE.txt
Requires-Dist: ipython
Requires-Dist: jupyter
Requires-Dist: matplotlib>=3.4
Requires-Dist: numpy
Requires-Dist: numba
Requires-Dist: scipy
Dynamic: license-file
